LICENSE
MANIFEST.in
README.rst
setup.py
pyramid_filterwarnings/__init__.py
pyramid_filterwarnings.egg-info/PKG-INFO
pyramid_filterwarnings.egg-info/SOURCES.txt
pyramid_filterwarnings.egg-info/dependency_links.txt
pyramid_filterwarnings.egg-info/not-zip-safe
pyramid_filterwarnings.egg-info/requires.txt
pyramid_filterwarnings.egg-info/top_level.txt