Metadata-Version: 1.1
Name: pyramid-filterwarnings
Version: 0.4
Summary: Configure python warnings for the Pyramid web framework
Home-page: https://github.com/mardiros/pyramid_filterwarnings
Author: Guillaume Gauvrit
Author-email: guillaume@gauvr.it
License: BSD
Keywords: pyramid
Platform: UNKNOWN
Classifier: Intended Audience :: Developers
Classifier: Programming Language :: Python
Classifier: Programming Language :: Python :: 2.6
Classifier: Programming Language :: Python :: 2.7
Classifier: Topic :: Internet :: WWW/HTTP
Classifier: Framework :: Pyramid
Classifier: License :: OSI Approved :: BSD License
